{
  "updated_at": "2026-06-30T13:52:04Z",
  "dataset_updated_at": "2026-06-30T13:52:04Z",
  "poll_notice_latest_detected_at": "2026-06-30T12:31:21Z",
  "timestamp_note": "updated_at and dataset_updated_at are derived from the latest canonical or staged-row timestamp. poll_notice_latest_detected_at is poll-notice discovery time.",
  "project": "France 2027 Monitor",
  "data_layer": "FR27 Open Data",
  "status": "prototype",
  "candidates": [
    {
      "candidate_id": "cand_attal",
      "display_name": "Gabriel Attal",
      "party": "Renaissance",
      "bloc": "Centre / Macron camp",
      "current_status": "tracked_public_actor",
      "color_hex": "#2F80ED",
      "latest_poll": null,
      "poll_change": null,
      "poll_unit": "%"
    },
    {
      "candidate_id": "cand_philippe",
      "display_name": "Édouard Philippe",
      "party": "Horizons",
      "bloc": "Centre-right",
      "current_status": "tracked_public_actor",
      "color_hex": "#00A3A3",
      "latest_poll": null,
      "poll_change": null,
      "poll_unit": "%"
    },
    {
      "candidate_id": "cand_melenchon",
      "display_name": "Jean-Luc Mélenchon",
      "party": "La France insoumise",
      "bloc": "Left",
      "current_status": "tracked_public_actor",
      "color_hex": "#C026D3",
      "latest_poll": null,
      "poll_change": null,
      "poll_unit": "%"
    }
  ],
  "events": [
    {
      "event_id": "evt_2026_0006",
      "event_date": "2026-03-09",
      "event_type": "public_meeting",
      "title": "Meeting de Jean-Luc Mélenchon à Paris",
      "candidate_id": "cand_melenchon",
      "candidate_name": "Jean-Luc Mélenchon",
      "location_name": "Paris",
      "commune": "Paris",
      "region": "Île-de-France",
      "latitude": 48.8566,
      "longitude": 2.3522,
      "source_name": "Jean-Luc Mélenchon official site",
      "source_url": "https://melenchon.fr/2026/03/09/meeting-avec-jean-luc-melenchon-et-sophia-chikirou-a-paris/",
      "verification_status": "verified_primary"
    },
    {
      "event_id": "evt_2026_0005",
      "event_date": "2026-05-10",
      "event_type": "party_event",
      "title": "Conseil national d'Horizons à Reims",
      "candidate_id": "cand_philippe",
      "candidate_name": "Édouard Philippe",
      "location_name": "Reims",
      "commune": "Reims",
      "region": "Grand Est",
      "latitude": 49.2583,
      "longitude": 4.0317,
      "source_name": "Horizons",
      "source_url": "https://horizonsleparti.fr/discours-dedouard-philippe-lors-du-conseil-national-a-reims-10-mai-2026/",
      "verification_status": "verified_primary"
    },
    {
      "event_id": "evt_2026_0001",
      "event_date": "2026-05-30",
      "event_type": "public_meeting",
      "title": "Grand meeting de Gabriel Attal à Paris",
      "candidate_id": "cand_attal",
      "candidate_name": "Gabriel Attal",
      "location_name": "Paris Expo Porte de Versailles - Hall 4",
      "commune": "Paris",
      "region": "Île-de-France",
      "latitude": 48.8302,
      "longitude": 2.2874,
      "source_name": "Renaissance",
      "source_url": "https://utilisateur.parti-renaissance.fr/grand-rassemblement/grand-meeting-du-30-mai",
      "verification_status": "verified_primary"
    },
    {
      "event_id": "evt_2026_0002",
      "event_date": "2026-06-07",
      "event_type": "public_meeting",
      "title": "Meeting national de Jean-Luc Mélenchon à Saint-Denis",
      "candidate_id": "cand_melenchon",
      "candidate_name": "Jean-Luc Mélenchon",
      "location_name": "Saint-Denis",
      "commune": "Saint-Denis",
      "region": "Île-de-France",
      "latitude": 48.9362,
      "longitude": 2.3574,
      "source_name": "Jean-Luc Mélenchon official site",
      "source_url": "https://melenchon.fr/2026/06/07/meeting-de-jean-luc-melenchon-a-saint-denis/",
      "verification_status": "verified_primary"
    },
    {
      "event_id": "evt_2026_0004",
      "event_date": "2026-06-27",
      "event_type": "public_meeting",
      "title": "Meeting de Gabriel Attal à Sanguinet",
      "candidate_id": "cand_attal",
      "candidate_name": "Gabriel Attal",
      "location_name": "Place du marché de Sanguinet",
      "commune": "Sanguinet",
      "region": "Nouvelle-Aquitaine",
      "latitude": 44.4847,
      "longitude": -1.0736,
      "source_name": "Renaissance",
      "source_url": "https://utilisateur.parti-renaissance.fr/grand-rassemblement/meeting-sanguinet",
      "verification_status": "verified_primary"
    },
    {
      "event_id": "evt_2026_0003",
      "event_date": "2026-07-05",
      "event_type": "public_meeting",
      "title": "Grand meeting d'Édouard Philippe à Paris",
      "candidate_id": "cand_philippe",
      "candidate_name": "Édouard Philippe",
      "location_name": "Adidas Arena Paris",
      "commune": "Paris",
      "region": "Île-de-France",
      "latitude": 48.8994,
      "longitude": 2.3606,
      "source_name": "Horizons",
      "source_url": "https://horizonsleparti.fr/",
      "verification_status": "verified_primary"
    }
  ],
  "latest_poll": {
    "poll_id": null,
    "institute": null,
    "publisher": null,
    "publication_date": null,
    "fieldwork": "None to None",
    "sample_size": null,
    "notice_url": null,
    "note": null
  },
  "poll_notice_status": {
    "status_label": "review_queue_active",
    "source_name": "Commission des sondages",
    "source_file": "staging/poll_notices_triaged_review.csv",
    "total_staged_notices": 87,
    "high_priority_review_count": 7,
    "canonical_poll_metadata_rows": 0,
    "canonical_poll_result_rows": 0,
    "candidate_level_values_extracted": false,
    "latest_detected_at": "2026-06-30T12:31:21Z",
    "triage_counts": {
      "candidate_or_field_context_notice": 10,
      "historical_reference": 2,
      "likely_presidential_voting_intention_notice": 7,
      "needs_manual_review": 29,
      "official_communique": 1,
      "political_barometer_context_notice": 37,
      "source_index_reference": 1
    },
    "review_priority_counts": {
      "high": 7,
      "low": 40,
      "medium": 40
    },
    "high_priority_examples": [
      {
        "poll_notice_stage_id": "poll_notice_stage_a15b32a660cd1a05",
        "link_text": "9961 Pres Toluna Harris Interactive Lopinion Suivi du potentiel électoral V2 27 juin",
        "notice_url": "https://www.commission-des-sondages.fr/notices/medias/fichiers/add/1942",
        "triage_label": "likely_presidential_voting_intention_notice"
      },
      {
        "poll_notice_stage_id": "poll_notice_stage_de917f3c5571775a",
        "link_text": "9975 Pres Toluna HI Suivi du potentiel électoral V3 Lopinion 3 septembre",
        "notice_url": "https://www.commission-des-sondages.fr/notices/medias/fichiers/add/1957",
        "triage_label": "likely_presidential_voting_intention_notice"
      },
      {
        "poll_notice_stage_id": "poll_notice_stage_3dfdf61fddcb4b47",
        "link_text": "10049 Pres potentiel vote RN CLUSTER 17 Marianne 14 janvier",
        "notice_url": "https://www.commission-des-sondages.fr/notices/medias/fichiers/add/2035",
        "triage_label": "likely_presidential_voting_intention_notice"
      },
      {
        "poll_notice_stage_id": "poll_notice_stage_c846a56414dcac91",
        "link_text": "10168 Pres Enquete electorale IPSOS BVA Le Monde 13 avril",
        "notice_url": "https://www.commission-des-sondages.fr/notices/medias/fichiers/add/2169",
        "triage_label": "likely_presidential_voting_intention_notice"
      },
      {
        "poll_notice_stage_id": "poll_notice_stage_32a4a8ed46edec82",
        "link_text": "10205 Pres IV OPINIONWAY JDD 13 juin",
        "notice_url": "https://www.commission-des-sondages.fr/notices/medias/fichiers/add/2210",
        "triage_label": "likely_presidential_voting_intention_notice"
      }
    ],
    "note": "Staged poll-notice discovery only. Candidate-level poll values are not extracted or displayed.",
    "metadata_review_status": {
      "source_file": "staging/poll_metadata_high_priority_review.csv",
      "total_review_rows": 7,
      "pending_review_count": 5,
      "ready_for_canonical_metadata_count": 0,
      "candidate_level_values_extracted": false,
      "examples": [
        {
          "review_queue_id": "poll_metadata_review_a15b32a660cd1a05",
          "notice_link_text": "9961 Pres Toluna Harris Interactive Lopinion Suivi du potentiel électoral V2 27 juin",
          "notice_url": "https://www.commission-des-sondages.fr/notices/medias/fichiers/add/1942",
          "metadata_review_decision": "defer",
          "ready_for_canonical_metadata": "false"
        },
        {
          "review_queue_id": "poll_metadata_review_de917f3c5571775a",
          "notice_link_text": "9975 Pres Toluna HI Suivi du potentiel électoral V3 Lopinion 3 septembre",
          "notice_url": "https://www.commission-des-sondages.fr/notices/medias/fichiers/add/1957",
          "metadata_review_decision": "defer",
          "ready_for_canonical_metadata": "false"
        },
        {
          "review_queue_id": "poll_metadata_review_3dfdf61fddcb4b47",
          "notice_link_text": "10049 Pres potentiel vote RN CLUSTER 17 Marianne 14 janvier",
          "notice_url": "https://www.commission-des-sondages.fr/notices/medias/fichiers/add/2035",
          "metadata_review_decision": "pending",
          "ready_for_canonical_metadata": "false"
        }
      ],
      "note": "Metadata-only manual review queue. Candidate-level poll values are not stored here."
    },
    "media_discovery_status": {
      "source_file": "staging/poll_media_mentions.csv",
      "query_feed_file": "staging/poll_media_query_feeds.csv",
      "query_feed_count": 3,
      "total_media_mentions": 30,
      "high_priority_count": 7,
      "medium_priority_count": 23,
      "low_priority_count": 0,
      "pending_review_count": 23,
      "promote_to_metadata_review_count": 7,
      "candidate_level_values_extracted": false,
      "latest_detected_at": "2026-06-29T09:48:11Z",
      "priority_counts": {
        "high": 7,
        "medium": 23
      },
      "label_counts": {
        "likely_poll_media_mention": 7,
        "possible_poll_media_mention": 23
      },
      "review_decision_counts": {
        "promote_to_metadata_review": 7,
        "pending": 23
      },
      "high_priority_examples": [
        {
          "source_name": "Ipsos",
          "article_title": "Présidentielle 2027 : le retour du vote sur enjeux ? - Ipsos",
          "article_url": "https://news.google.com/rss/articles/CBMiggFBVV95cUxPTXZiSFBtbHRZMkVReU53cXBJNjJqZEROR3dseFQwR05QeE42ODNBZTktWUF2QmVLdXQxSG1GMml1bG5hQzdzaUVHM0VsM0dpdWdVMF9oUzdUZVJqRzhOSEQwSDZiYldaN1VtbW9iZU81LUZ2VWFRRnJIUDFWRUlZMWNB?oc=5",
          "published_at": "2026-04-13T07:00:00Z",
          "possible_institute": "Ipsos"
        },
        {
          "source_name": "franceinfo",
          "article_title": "Présidentielle 2027 : s'en remettre aux sondages révèle \"une forme d'impuissance du politique à dégager des personnalités qui font consensus\", note Christelle Craplet, directrice opinion Ipsos-BVA - franceinfo",
          "article_url": "https://news.google.com/rss/articles/CBMi7wJBVV95cUxNRzdIaXEyQThKaGo4dXViMVVySkp3OGRBejlFc2t6ck5kd3R1M1Q2MExDS0ZuRlNoNlJNbnE3Yl9qZHFhWmlyWXZUWGdocFRONVo5eFRud1o5OVpWVjVRUXZ0VUR1cVlVTElKTjVEOUdvb3UybGZ1ZHdkeE9TNU1NWDkwWVhYUmdFZzU4ZmNTbnhpLUh",
          "published_at": "2026-04-29T07:00:00Z",
          "possible_institute": "Ipsos; BVA"
        },
        {
          "source_name": "tolunacorporate.com",
          "article_title": "Intentions de vote à l’élection présidentielle 2027 - tolunacorporate.com",
          "article_url": "https://news.google.com/rss/articles/CBMihgFBVV95cUxPQkVIQ05ZZ1R1bGFhVlRtc3hWMzFfS2ZMTzFxNVBxTUt1YmVKLWFDcU9rOEJOalJ6SlZZUzB0dDNKTjQ1M3czMXFWWDNKc2hFWlBaTUFhU29GZlBmTjhBY1VoaTVUOUViMnpYb1MyVHB6MXRGdEM4Z1FPUjMtWkhuOUtFazVTZw?oc=5",
          "published_at": "2026-05-04T07:00:00Z",
          "possible_institute": "Toluna"
        }
      ],
      "note": "Staged media-discovery metadata only. No article scraping and no candidate-level poll values."
    }
  }
}
